{"name":"build-javascript","namedChunkGroups":{"app":{"name":"app","assets":[{"name":"webpack-runtime-8636eaf52e3eca301bdd.js","size":5392},{"name":"framework-8cb3c00d0f3b2aabea4b.js","size":141426},{"name":"app-e83e686d0cfd22bde309.js","size":68915}],"filteredAssets":0,"assetsSize":215733,"filteredAuxiliaryAssets":3,"auxiliaryAssetsSize":617786},"component---src-pages-404-js":{"name":"component---src-pages-404-js","assets":[{"name":"styles.a92e043071832cadbced.css","size":28692},{"name":"c16184b3-dc957559ce818e7364e3.js","size":1645},{"name":"2cca2479-ec578ff47ac4e4f7cb80.js","size":2356},{"name":"commons-dd6c98460eec2face205.js","size":107761},{"name":"component---src-pages-404-js-a0e445f9b03d141c0129.js","size":516}],"filteredAssets":0,"assetsSize":140970,"filteredAuxiliaryAssets":5,"auxiliaryAssetsSize":6858489},"component---src-pages-about-js":{"name":"component---src-pages-about-js","assets":[{"name":"styles.a92e043071832cadbced.css","size":28692},{"name":"framework-8cb3c00d0f3b2aabea4b.js","size":141426},{"name":"c16184b3-dc957559ce818e7364e3.js","size":1645},{"name":"2cca2479-ec578ff47ac4e4f7cb80.js","size":2356},{"name":"commons-dd6c98460eec2face205.js","size":107761},{"name":"d4ad233efeb1d959420253442063e6db7488fdeb-0e42c77705824a47d3d3.js","size":74932},{"name":"component---src-pages-about-js-01a6d8b684c93fe0ad85.js","size":6251}],"filteredAssets":0,"assetsSize":363063,"filteredAuxiliaryAssets":7,"auxiliaryAssetsSize":7609400},"component---src-pages-groups-js":{"name":"component---src-pages-groups-js","assets":[{"name":"styles.a92e043071832cadbced.css","size":28692},{"name":"c16184b3-dc957559ce818e7364e3.js","size":1645},{"name":"2cca2479-ec578ff47ac4e4f7cb80.js","size":2356},{"name":"commons-dd6c98460eec2face205.js","size":107761},{"name":"f601eaf97811367ad3ad00fa331821e5bdabe34b-dfd26e0f4d8123a63ffb.js","size":10340},{"name":"component---src-pages-groups-js-284635558f27ed5a0af7.js","size":20739}],"filteredAssets":0,"assetsSize":171533,"filteredAuxiliaryAssets":6,"auxiliaryAssetsSize":6950544},"component---src-pages-index-js":{"name":"component---src-pages-index-js","assets":[{"name":"styles.a92e043071832cadbced.css","size":28692},{"name":"framework-8cb3c00d0f3b2aabea4b.js","size":141426},{"name":"c16184b3-dc957559ce818e7364e3.js","size":1645},{"name":"2cca2479-ec578ff47ac4e4f7cb80.js","size":2356},{"name":"commons-dd6c98460eec2face205.js","size":107761},{"name":"d4ad233efeb1d959420253442063e6db7488fdeb-0e42c77705824a47d3d3.js","size":74932},{"name":"f601eaf97811367ad3ad00fa331821e5bdabe34b-dfd26e0f4d8123a63ffb.js","size":10340},{"name":"component---src-pages-index-js-5d4c7031a0865972687b.js","size":18880}],"filteredAssets":0,"assetsSize":386032,"filteredAuxiliaryAssets":8,"auxiliaryAssetsSize":7707434},"component---src-pages-using-ssr-js":{"name":"component---src-pages-using-ssr-js","assets":[{"name":"styles.a92e043071832cadbced.css","size":28692},{"name":"c16184b3-dc957559ce818e7364e3.js","size":1645},{"name":"2cca2479-ec578ff47ac4e4f7cb80.js","size":2356},{"name":"commons-dd6c98460eec2face205.js","size":107761},{"name":"component---src-pages-using-ssr-js-1b9b9f35c89e583c3547.js","size":1136}],"filteredAssets":0,"assetsSize":141590,"filteredAuxiliaryAssets":5,"auxiliaryAssetsSize":6859899},"component---src-pages-using-typescript-tsx":{"name":"component---src-pages-using-typescript-tsx","assets":[{"name":"styles.a92e043071832cadbced.css","size":28692},{"name":"c16184b3-dc957559ce818e7364e3.js","size":1645},{"name":"2cca2479-ec578ff47ac4e4f7cb80.js","size":2356},{"name":"commons-dd6c98460eec2face205.js","size":107761},{"name":"component---src-pages-using-typescript-tsx-0d0ecb5e3bb9d6534a9c.js","size":1467}],"filteredAssets":0,"assetsSize":141921,"filteredAuxiliaryAssets":5,"auxiliaryAssetsSize":6860265},"component---src-templates-using-dsg-js":{"name":"component---src-templates-using-dsg-js","assets":[{"name":"styles.a92e043071832cadbced.css","size":28692},{"name":"c16184b3-dc957559ce818e7364e3.js","size":1645},{"name":"2cca2479-ec578ff47ac4e4f7cb80.js","size":2356},{"name":"commons-dd6c98460eec2face205.js","size":107761},{"name":"component---src-templates-using-dsg-js-1cae88d312654c0874cb.js","size":856}],"filteredAssets":0,"assetsSize":141310,"filteredAuxiliaryAssets":5,"auxiliaryAssetsSize":6858968}},"assetsByChunkName":{"app":["webpack-runtime-8636eaf52e3eca301bdd.js","framework-8cb3c00d0f3b2aabea4b.js","app-e83e686d0cfd22bde309.js"],"component---src-pages-404-js":["styles.a92e043071832cadbced.css","c16184b3-dc957559ce818e7364e3.js","2cca2479-ec578ff47ac4e4f7cb80.js","commons-dd6c98460eec2face205.js","component---src-pages-404-js-a0e445f9b03d141c0129.js"],"component---src-pages-about-js":["styles.a92e043071832cadbced.css","framework-8cb3c00d0f3b2aabea4b.js","c16184b3-dc957559ce818e7364e3.js","2cca2479-ec578ff47ac4e4f7cb80.js","commons-dd6c98460eec2face205.js","d4ad233efeb1d959420253442063e6db7488fdeb-0e42c77705824a47d3d3.js","component---src-pages-about-js-01a6d8b684c93fe0ad85.js"],"component---src-pages-groups-js":["styles.a92e043071832cadbced.css","c16184b3-dc957559ce818e7364e3.js","2cca2479-ec578ff47ac4e4f7cb80.js","commons-dd6c98460eec2face205.js","f601eaf97811367ad3ad00fa331821e5bdabe34b-dfd26e0f4d8123a63ffb.js","component---src-pages-groups-js-284635558f27ed5a0af7.js"],"component---src-pages-index-js":["styles.a92e043071832cadbced.css","framework-8cb3c00d0f3b2aabea4b.js","c16184b3-dc957559ce818e7364e3.js","2cca2479-ec578ff47ac4e4f7cb80.js","commons-dd6c98460eec2face205.js","d4ad233efeb1d959420253442063e6db7488fdeb-0e42c77705824a47d3d3.js","f601eaf97811367ad3ad00fa331821e5bdabe34b-dfd26e0f4d8123a63ffb.js","component---src-pages-index-js-5d4c7031a0865972687b.js"],"component---src-pages-using-ssr-js":["styles.a92e043071832cadbced.css","c16184b3-dc957559ce818e7364e3.js","2cca2479-ec578ff47ac4e4f7cb80.js","commons-dd6c98460eec2face205.js","component---src-pages-using-ssr-js-1b9b9f35c89e583c3547.js"],"component---src-pages-using-typescript-tsx":["styles.a92e043071832cadbced.css","c16184b3-dc957559ce818e7364e3.js","2cca2479-ec578ff47ac4e4f7cb80.js","commons-dd6c98460eec2face205.js","component---src-pages-using-typescript-tsx-0d0ecb5e3bb9d6534a9c.js"],"component---src-templates-using-dsg-js":["styles.a92e043071832cadbced.css","c16184b3-dc957559ce818e7364e3.js","2cca2479-ec578ff47ac4e4f7cb80.js","commons-dd6c98460eec2face205.js","component---src-templates-using-dsg-js-1cae88d312654c0874cb.js"]},"childAssetsByChunkName":{}}